<?xml version="1.0" encoding="utf-8"?>
<animNode>
	<m_Name>runcartleft</m_Name>
	<m_AnimName>Bob_Cart_Run</m_AnimName>
	<m_Priority>10</m_Priority>
	<m_ConditionPriority>10</m_ConditionPriority>
	<m_SpeedScale>1.30</m_SpeedScale>
	<m_Conditions>
		<m_Name>LeftHandMask</m_Name>
		<m_Type>STRING</m_Type>
		<m_Value>holdingcartleft</m_Value>
	</m_Conditions>
	<m_Conditions>
		<m_Name>isMoving</m_Name>
		<m_Type>BOOL</m_Type>
		<m_Value>true</m_Value>
	</m_Conditions>
	<m_Conditions>
		<m_Name>isRunning</m_Name>
		<m_Type>BOOL</m_Type>
		<m_Value>true</m_Value>
	</m_Conditions>
	<m_Conditions>
		<m_Name>isSprinting</m_Name>
		<m_Type>BOOL</m_Type>
		<m_Value>false</m_Value>
	</m_Conditions>
	<m_Conditions>
		<m_Name>Aim</m_Name>
		<m_Type>BOOL</m_Type>
		<m_Value>false</m_Value>
	</m_Conditions>
	<m_Conditions>
		<m_Name>sneaking</m_Name>
		<m_Type>BOOL</m_Type>
		<m_Value>false</m_Value>
	</m_Conditions>
	<m_Transitions>
		<m_Target>sprintcartleft</m_Target>
		<m_blendInTime>0.2</m_blendInTime>
		<m_blendOutTime>0.2</m_blendOutTime>
	</m_Transitions>
	<m_Transitions>
		<m_Target>holdingcartleft</m_Target>
		<m_blendInTime>0.3</m_blendInTime>
		<m_blendOutTime>0.3</m_blendOutTime>
	</m_Transitions>
	<m_Transitions>
		<m_Target>walkcartleft</m_Target>
		<m_blendInTime>0.3</m_blendInTime>
		<m_blendOutTime>0.3</m_blendOutTime>
	</m_Transitions>
	<m_SubStateBoneWeights>
		<boneName>Bip01</boneName>
		<weight>0.00</weight>
	</m_SubStateBoneWeights>
	<m_SubStateBoneWeights>
		<boneName>Bip01_Prop2</boneName>
		<weight>1.00</weight>
	</m_SubStateBoneWeights>
</animNode>
